myads/__init__.py
myads/_version.py
myads/query.py
myads/scripts/cite_tracker.py
myads-2.0.0.dist-info/METADATA
myads-2.0.0.dist-info/WHEEL
myads-2.0.0.dist-info/entry_points.txt
myads-2.0.0.dist-info/top_level.txt
myads-2.0.0.dist-info/RECORD
