Metadata-Version: 2.4
Name: myads
Version: 2.0.0
Summary: Simple ADS API query package and citation tracker
Author-email: Stuart McAlpine <stuart.mcalpine@fysik.su.se>
License: BSD 3-Clause License
Project-URL: homepage, https://github.com/stuartmcalpine/myADS
Project-URL: repository, https://github.com/stuartmcalpine/myADS
Keywords: nasa-ads,citations,astronomy,ads,python,arxiv
Classifier: Programming Language :: Python :: 3
Requires-Python: >=3.7
Requires-Dist: requests
Requires-Dist: toml
Requires-Dist: tabulate>=0.9.0
Requires-Dist: pandas
Requires-Dist: sqlalchemy
Requires-Dist: rich
